asyncflows/__init__.py
asyncflows/actions/__init__.py
asyncflows/actions/execute_db_statement.py
asyncflows/actions/extract_list.py
asyncflows/actions/extract_pdf_text.py
asyncflows/actions/extract_xml_tag.py
asyncflows/actions/get_db_schema.py
asyncflows/actions/get_url.py
asyncflows/actions/ocr.py
asyncflows/actions/prompt.py
asyncflows/actions/score.py
asyncflows/actions/transformer.py
asyncflows/actions/utils/__init__.py
asyncflows/actions/utils/prompt_context.py
asyncflows/asyncflows.py
asyncflows/examples/__init__.py
asyncflows/examples/application_information/application.txt
asyncflows/examples/application_information/application_criteria.txt
asyncflows/examples/application_judgement.py
asyncflows/examples/application_judgement.yaml
"asyncflows/examples/books/Alice's Adventures in Wonderland, by Lewis Carroll.pdf"
asyncflows/examples/chatbot.py
asyncflows/examples/chatbot.yaml
asyncflows/examples/debono.py
asyncflows/examples/debono.yaml
asyncflows/examples/get_page_title.py
asyncflows/examples/get_page_title.yaml
asyncflows/examples/hello_world.py
asyncflows/examples/hello_world.yaml
asyncflows/examples/meeting_review.py
asyncflows/examples/meeting_review.yaml
asyncflows/examples/rag.py
asyncflows/examples/rag.yaml
asyncflows/examples/recipes/caprese.md
asyncflows/examples/recipes/chana_masala.md
asyncflows/examples/recipes/coconut_soup.md
asyncflows/examples/recipes/gazpacho.md
asyncflows/examples/recipes/guacamole.md
asyncflows/examples/recipes/hummus.md
asyncflows/examples/recipes/miso_soup.md
asyncflows/examples/recipes/omelette.md
asyncflows/examples/recipes/stir_fry.md
asyncflows/examples/recipes/yogurt_parfait.md
asyncflows/examples/sql_rag.py
asyncflows/examples/sql_rag.yaml
asyncflows/examples/text_style_transfer.py
asyncflows/examples/text_style_transfer.yaml
asyncflows/log_config.py
asyncflows/models/__init__.py
asyncflows/models/blob.py
asyncflows/models/config/__init__.py
asyncflows/models/config/action.py
asyncflows/models/config/common.py
asyncflows-0.1.11.dist-info/LICENSE
asyncflows-0.1.11.dist-info/METADATA
asyncflows-0.1.11.dist-info/WHEEL
asyncflows-0.1.11.dist-info/entry_points.txt
asyncflows-0.1.11.dist-info/RECORD
